{
  "title": "Что такое Dasein у Мартина Хайдеггера?",
  "date": "2023-05-20",
  "content": "<p>Мартин Хайдеггер, титан философии XX века, бился над фундаментальным вопросом о «бытии». Он считал, что западная философия сбилась с пути, сосредоточившись на отдельных сущностях, а не на всеобъемлющей концепции самого Бытия. В труде «Бытие и время» (1927) Хайдеггер ввел термин «Dasein», который произвел революцию в нашем понимании человеческого опыта.</p><strong>Dasein, часто переводимый как «бытие-в-мире» или «существование», выходит за рамки традиционных философских взглядов, рассматривающих человека как объект анализа.</strong> Хайдеггер настаивает на том, что мы - не отстраненные наблюдатели, а существа, неразрывно связанные с миром. Мы - «бытие-в-мире», постоянно погруженное в паутину отношений, забот и возможностей.<strong> Это «бытие-в-мире» не статично, а глубоко темпорально.</strong> Dasein существует в вечном потоке времени, формируемом грузом прошлого, предвкушением будущего и непосредственностью настоящего. Эта динамичная темпоральность окрашивает наше понимание Бытия и наполняет наше существование смыслом и срочностью.<p>Хайдеггер утверждает, что «забота» - это определяющая характеристика Dasein. <strong>Мы - существа, вечно чем-то озабоченные, движимые целями, желаниями и тревогами.</strong> Мы ориентируемся в мире возможностей и ограничений, постоянно делая выбор, который формирует наше существование. Эта структура «заботы» подчеркивает нашу фундаментальную вовлеченность в мир и подчеркивает экзистенциальную природу человеческого опыта.</p><strong>Осознание Dasein своей конечности и неизбежности смерти еще больше обостряет его отношения с Бытием.</strong> Это «бытие навстречу смерти» - не болезненная одержимость, а катализатор подлинной жизни. Оно заставляет нас противостоять своим ограничениям, брать на себя ответственность за свой выбор и жить с целью и намерением.<p>Хайдеггер различает <strong>аутентичный</strong> и <strong>неаутентичный</strong> способы существования. Аутентичность возникает из противостояния нашей ограниченности, принятия нашей свободы и жизни в соответствии с нашим истинным «я». Неаутентичность, напротив, проистекает из уклонения от нашей экзистенциальной реальности, соответствия давлению общества и жизни в состоянии самообмана.</p><strong>Понимание Dasein требует изменения перспективы.</strong> Мы должны отойти от абстрактных концептуализаций человеческого субъекта и погрузиться в живой опыт бытия-в-мире. Dasein - это не объект, который нужно препарировать, а динамичное, временное и заботливое существование, которое размышляет над глубоким вопросом о бытии.<p>Хайдеггеровская концепция Dasein оказала глубокое влияние на философскую мысль, особенно в таких областях, как экзистенциализм, феноменология и герменевтика. Его работы заставляют нас переосмыслить свое место в мире, столкнуться с нашей смертностью и стремиться к подлинности в мире, который часто характеризуется неаутентичностью.</p><p>Хотя представленные источники дают представление о сложности Dasein, углубление в «Бытие и время» и изучение вторичных интерпретаций имеет решающее значение для всестороннего понимания этого важнейшего понятия. Dasein - это не статичное определение, а приглашение к постоянному философскому исследованию того, что значит быть человеком.</p>",
  "excerpt": "Краткое описание статьи",
  "tags": ["Хайдеггер"],
  "theme": "Философия"
}
