{
  "title": "Ungrund Якоба Бёме",
  "date": "2025-03-08",
  "content": "<p>Якоба Бёме, немецкий мистик XVII века, разрабатывает идеи, значительно выходящие за пределы традиционной христианской метафизики. Центральное место в его космологии занимает концепция <strong>Ungrund</strong>, что буквально переводится как «бездна» или «неоснова». Этот термин выражает изначальное состояние до сотворения мира, нечто непостижимое и неописуемое, стоящее за пределами как бытия, так и небытия.</p><p><strong>Ungrund</strong> у Бёме — это не просто отсутствие основания, но <strong>абсолютная свобода</strong>, в которой еще нет даже идеи различия. В этом смысле Ungrund ближе к потенции, чем к пустоте. В нем содержится возможность как света, так и тьмы, но еще нет никаких различий, которые бы могли проявиться в конкретной форме. Это состояние характеризуется <strong>предвечной волей</strong>, которая не обусловлена ничем, кроме самой себя.</p><p>Воля, исходящая из Ungrund, создает движение, которое Бёме называет «вечным желанием». Это желание порождает напряжение, из которого происходит манифестация всего существующего. Здесь важно, что <strong>сотворение мира</strong> у Бёме не является разовым актом: это <strong>постоянный процесс</strong>, в котором Ungrund непрестанно порождает новое через волю и желание.</p><p>В этом контексте Бёме вводит понятие <strong>Qual</strong>, что можно перевести как «мучение» или «страдание». Qual — это неизбежное следствие движения воли, когда потенциальное начинает переходить в актуальное. Struggle (борьба) здесь не случайна, а необходима, так как именно через страдание проявляется форма, возникает определенность из неопределенности.</p><p>Бёме также развивает идею, что через Ungrund и Qual становится возможным <strong>самопознание Бога</strong>. Бог осознает себя не через статическое бытие, а через динамику собственного проявления в мире. Это радикально отличает его учение от классической теологии, где Бог часто рассматривается как неизменная и полностью завершенная сущность.</p><p>Свет и тьма у Бёме не просто противоположности, но <strong>две стороны одного процесса</strong>. Свет рождается не сам по себе, а только через преодоление тьмы, через Qual. Таким образом, Ungrund — это не просто хаос или ничто, но <strong>источник всех возможностей</strong>, который только в процессе проявления становится бытием.</p><p>Философия Бёме, в особенности его концепция Ungrund, ставит под сомнение идею абсолютной устойчивости бытия. В его учении мир — это не результат конечного акта творения, а <strong>бесконечная трансформация</strong>, в которой каждое мгновение удерживается на грани между потенциальным и актуальным, между свободой и необходимостью.</p>",
  "theme": "phi",
  "tags": ["Беме", "Мистицизм"],
  "id": "ungrund-yakoba-beme"
}